q3operations/__init__.py
q3operations/operations.py
q3operations-0.0.7.dist-info/METADATA
q3operations-0.0.7.dist-info/WHEEL
q3operations-0.0.7.dist-info/top_level.txt
q3operations-0.0.7.dist-info/RECORD
